BEMEWS/__init__.py
BEMEWS/_ext.cpython-310-darwin.so
BEMEWS/data/PREM.Ye.dat
BEMEWS/data/PREM.rho.dat
BEMEWS/data/__init__.py
BEMEWS-1.0a1.dist-info/LICENSE
BEMEWS-1.0a1.dist-info/METADATA
BEMEWS-1.0a1.dist-info/WHEEL
BEMEWS-1.0a1.dist-info/top_level.txt
BEMEWS-1.0a1.dist-info/RECORD
