Metadata-Version: 2.1
Name: BEMEWS
Version: 1.0a1
Summary: A Python module for computing the Earth-matter effect upon neutrinos. Works alone or with snewpy.
Author: Anne Graf
Author-email: Jim Kneller <jpknelle@ncsu.edu>
License: BSD License
Project-URL: Homepage, https://github.com/SNEWS2/BEMEWS
Requires-Python: >=3.9
License-File: LICENSE
Requires-Dist: numpy>=1.16
Requires-Dist: scipy
Requires-Dist: astropy>=4.3
